AUTHORS
LICENSE
MANIFEST.in
README.rst
flask_kerberos.py
setup.py
Flask_Kerberos.egg-info/PKG-INFO
Flask_Kerberos.egg-info/SOURCES.txt
Flask_Kerberos.egg-info/dependency_links.txt
Flask_Kerberos.egg-info/not-zip-safe
Flask_Kerberos.egg-info/requires.txt
Flask_Kerberos.egg-info/top_level.txt