Metadata-Version: 1.1
Name: Flask-Kerberos
Version: 1.0.4
Summary: Kerberos authentication support for Flask
Home-page: http://github.com/mkomitee/flask-kerberos
Author: Michael Komitee
Author-email: mkomitee@gmail.com
License: BSD
Platform: any
Classifier: Development Status :: 4 - Beta
Classifier: Environment :: Web Environment
Classifier: Intended Audience :: Developers
Classifier: License :: OSI Approved :: BSD License
Classifier: Operating System :: OS Independent
Classifier: Programming Language :: Python
Classifier: Topic :: Internet :: WWW/HTTP
Classifier: Topic :: Software Development :: Libraries :: Python Modules
